soviet_calendar.py
sovietcalendar-1.0.0.dist-info/licenses/LICENSE
sovietcalendar-1.0.0.dist-info/METADATA
sovietcalendar-1.0.0.dist-info/WHEEL
sovietcalendar-1.0.0.dist-info/top_level.txt
sovietcalendar-1.0.0.dist-info/RECORD
