Metadata-Version: 2.4
Name: SovietCalendar
Version: 1.0.0
Summary: A lightweight Python utility to interpret Gregorian dates within the historical context of the Soviet work-week experiments (1929–1940).
Author-email: Nicolas Flandrois <contacts@flandrois.com>
Maintainer-email: Nicolas Flandrois <nicolas.dev@flandrois.com>
License:                     GNU GENERAL PUBLIC LICENSE
Project-URL: Homepage, https://github.com/NicolasFlandrois/Soviet-Calendar-Python-Package
Project-URL: GitHub, https://github.com/NicolasFlandrois/Soviet-Calendar-Python-Package
Classifier: Programming Language :: Python :: 3
Classifier: License :: OSI Approved :: GNU General Public License v3 (GPLv3)
Classifier: Operating System :: OS Independent
Requires-Python: >=3.14
License-File: LICENSE
Dynamic: license-file
